[{"WEB":"ManoloWeb","LUNES":"11111111","MARTES":"22222222","MIERCOLES":"33333","JUEVES":"66666","VIERNES":"1.23","SABADO":"191919","DOMINGO":"121231","TELEFONO":65748490,"NOMBRE":"Manolo","UTM_X":377174.53,"UTM_Y":3149714.5},{"WEB":"LobertaWeb","LUNES":"11111111","MARTES":"22222222","MIERCOLES":"33333","JUEVES":"66666","VIERNES":"1.23","SABADO":"191919","DOMINGO":"121231","TELEFONO":6098761,"NOMBRE":"Loberta","UTM_X":378901.4,"UTM_Y":3151710.2},{"WEB":"VictoriaWeb","LUNES":"11111111","MARTES":"22222222","MIERCOLES":"33333","JUEVES":"66666","VIERNES":"1.23","SABADO":"191919","DOMINGO":"121231","TELEFONO":4566960,"NOMBRE":"Victoria","UTM_X":377645.72,"UTM_Y":3145768.2},{"WEB":"AlbertoWeb","LUNES":"11111111","MARTES":"22222222","MIERCOLES":"33333","JUEVES":"66666","VIERNES":"1.23","SABADO":"191919","DOMINGO":"121231","TELEFONO":4566960,"NOMBRE":"Alberto","UTM_X":377607.8,"UTM_Y":3130304.2}]